fediverse_pasture/__init__.py
fediverse_pasture/__main__.py
fediverse_pasture/helper.py
fediverse_pasture/http_signature.py
fediverse_pasture/one_actor.py
fediverse_pasture/test_helper.py
fediverse_pasture/types.py
fediverse_pasture/verify_actor.py
fediverse_pasture/version.py
fediverse_pasture/data_provider/__init__.py
fediverse_pasture/data_provider/generate.py
fediverse_pasture/data_provider/models.py
fediverse_pasture/data_provider/test_data_provider.py
fediverse_pasture/data_provider/test_generate.py
fediverse_pasture/runner/__init__.py
fediverse_pasture/runner/config.py
fediverse_pasture/runner/entry.py
fediverse_pasture/runner/models.py
fediverse_pasture/runner/result_store.py
fediverse_pasture/runner/test_activity_runner.py
fediverse_pasture/runner/test_activity_sender.py
fediverse_pasture/runner/test_entry.py
fediverse_pasture/runner/test_result_store.py
fediverse_pasture/runner/test_verify_actor.py
fediverse_pasture/runner/verify_actor.py
fediverse_pasture/runner/application/__init__.py
fediverse_pasture/runner/application/bovine.py
fediverse_pasture/runner/application/firefish.py
fediverse_pasture/runner/application/mastodon.py
fediverse_pasture/runner/application/misskey.py
fediverse_pasture/runner/application/test_application.py
fediverse_pasture/runner/util/__init__.py
fediverse_pasture/runner/util/adjust_objects.py
fediverse_pasture/runner/util/id_maker.py
fediverse_pasture/runner/util/test_adjust_objects.py
fediverse_pasture/runner/util/test_id_maker.py
fediverse_pasture/send/__init__.py
fediverse_pasture/send/__main__.py
fediverse_pasture/send/modifier.py
fediverse_pasture/send/test_modifier.py
fediverse_pasture/server/__init__.py
fediverse_pasture/server/http_signature.py
fediverse_pasture/server/image_provider_blueprint.py
fediverse_pasture/server/nodeinfo_blueprint.py
fediverse_pasture/server/one_actor_app.py
fediverse_pasture/server/parser.py
fediverse_pasture/server/test_actor_public_key.py
fediverse_pasture/server/test_assets_blueprint.py
fediverse_pasture-0.2.25.dist-info/METADATA
fediverse_pasture-0.2.25.dist-info/WHEEL
fediverse_pasture-0.2.25.dist-info/licenses/LICENSE
fediverse_pasture-0.2.25.dist-info/RECORD
