Metadata-Version: 2.4
Name: fediverse-pasture
Version: 0.2.25
Summary: Helpful tools to test Fediverse Applications
Project-URL: repository, https://codeberg.org/funfedidev/python_fediverse_pasture
Project-URL: documentation, https://funfedi.dev/python_package/
Project-URL: homepage, https://funfedidev.codeberg.page/python_fediverse_pasture/
License-File: LICENSE
Requires-Python: >=3.11
Requires-Dist: bovine>=0.5.11
Requires-Dist: click>=8.2.0
Requires-Dist: pillow>=11.0.0
Requires-Dist: pydantic>=2.3.0
Requires-Dist: quart>=0.19.3
Requires-Dist: tomli-w>=1.0.0
Requires-Dist: tortoise-orm>=0.20.0
Requires-Dist: uvicorn>=0.28.0
